pelican/plugins/share_post/__init__.py
pelican/plugins/share_post/conftest.py
pelican/plugins/share_post/share_post.py
pelican/plugins/share_post/test_share_post.py
pelican_share_post-1.2.1.dist-info/METADATA
pelican_share_post-1.2.1.dist-info/WHEEL
pelican_share_post-1.2.1.dist-info/entry_points.txt
pelican_share_post-1.2.1.dist-info/RECORD
