Metadata-Version: 2.1
Name: pelican-share-post
Version: 1.2.1
Summary: A Pelican plugin to create share URLs of article
Keywords: pelican,plugin,social
Author-Email: Talha Mansoor <talha131@gmail.com>, Justin Mayer <entroP@gmail.com>
License: MIT
Classifier: Development Status :: 5 - Production/Stable
Classifier: Environment :: Console
Classifier: Framework :: Pelican
Classifier: Framework :: Pelican :: Plugins
Classifier: Intended Audience :: End Users/Desktop
Classifier: License :: OSI Approved :: MIT License
Classifier: Operating System :: OS Independent
Classifier: Programming Language :: Python :: 3
Classifier: Programming Language :: Python :: 3.8
Classifier: Programming Language :: Python :: 3.9
Classifier: Programming Language :: Python :: 3.10
Classifier: Programming Language :: Python :: 3.11
Classifier: Programming Language :: Python :: 3.12
Classifier: Topic :: Internet :: WWW/HTTP
Classifier: Topic :: Software Development :: Libraries :: Python Modules
Project-URL: Homepage, https://github.com/pelican-plugins/share-post
Project-URL: Issue Tracker, https://github.com/pelican-plugins/share-post/issues
Project-URL: Funding, https://donate.getpelican.com/
Requires-Python: <4.0,>=3.8.1
Requires-Dist: pelican>=4.5
Requires-Dist: beautifulsoup4>=4.9.3
Provides-Extra: markdown
Requires-Dist: markdown>=3.4; extra == "markdown"
